wordsolver/__init__.py
wordsolver/boggle.py
wordsolver/hangman.py
wordsolver/scrabble.py
wordsolver/wordsearch.py
wordsolver/wordtools.py
wordsolver-1.0.1.dist-info/LICENSE
wordsolver-1.0.1.dist-info/METADATA
wordsolver-1.0.1.dist-info/WHEEL
wordsolver-1.0.1.dist-info/top_level.txt
wordsolver-1.0.1.dist-info/RECORD
