Metadata-Version: 2.1
Name: wordsolver
Version: 1.0.1
Summary: A package to solve word games
Home-page: https://github.com/chrismalcolm/solver
Author: Christopher Malcolm
Author-email: chris.c.malcolm.96@gmail.com
License: MIT
Platform: UNKNOWN
Classifier: Programming Language :: Python :: 3
Classifier: Programming Language :: Python :: 3.6
Classifier: Programming Language :: Python :: 3.7
Classifier: Programming Language :: Python :: 3.8
Requires-Dist: numpy (>=1.19.2)
Requires-Dist: pythonds (>=1.2.1)
